{
    "type": "Screen",
    "translatedName": "Screen",
    "reactType": "ViewWithProps",
    "properties": {
        "Height": "Fill container",
        "Width": "Fill container",
        "Layout": "column",
        "BackgroundColor": "rgba(252, 179, 179, 1)",
        "Justification": "center",
        "Alignment": "center",
        "Visible": true,
        "style": {
            "marginTop": 0,
            "marginBottom": 0,
            "marginLeft": 0,
            "marginRight": 0,
            "paddingTop": 0,
            "paddingBottom": 0,
            "paddingLeft": 0,
            "paddingRight": 0,
            "shadowColor": "rgba(0, 0, 0, 0)",
            "shadowOpacity": 0,
            "scaledShadowOpacity": 0,
            "shadowRadius": 0,
            "shadowOffset": {
                "width": 0,
                "height": 0
            },
            "flexDirection": "column",
            "justifyContent": "center",
            "alignItems": "center",
            "display": "flex",
            "backgroundColor": "rgba(252, 179, 179, 1)"
        },
        "ShowStatusBar": true,
        "StatusBarStyle": "default",
        "TranslucentStatusBar": false,
        "StatusBarColor": "rgba(0,0,0,0.53)",
        "TabNavigationOptions": {
            "tabBarVisible": true
        },
        "TabNavigatorIcon": {},
        "DrawerNavigationOptions": {},
        "StackNavigationOptions": {
            "headerStyle": {}
        },
        "ScreenOrientation": "portrait",
        "DesignerHeight": 667,
        "DesignerWidth": 375,
        "ResponsiveWidth": 375,
        "isSimple": true,
        "navigationOptions": {
            "headerStyle": {}
        },
        "tabNavigationOptions": {}
    },
    "children": [
        {
            "type": "Image",
            "translatedName": "Image",
            "properties": {
                "Picture": "305soft-high-resolution-color-logo.png",
                "resizeMode": "stretch",
                "Height": 120,
                "Width": 158,
                "Visible": true,
                "X": 210,
                "Y": 532,
                "RelativeX": 210,
                "RelativeY": 532,
                "ResizeMode": "STRETCH",
                "style": {
                    "marginTop": 0,
                    "marginBottom": 0,
                    "marginLeft": 0,
                    "marginRight": 0,
                    "paddingTop": 0,
                    "paddingBottom": 0,
                    "paddingLeft": 0,
                    "paddingRight": 0,
                    "shadowColor": "rgba(0, 0, 0, 0)",
                    "shadowOpacity": 0,
                    "scaledShadowOpacity": 0,
                    "shadowRadius": 0,
                    "shadowOffset": {
                        "width": 0,
                        "height": 0
                    },
                    "position": "absolute",
                    "left": "31.920003255208332%",
                    "top": "75.09370314842579%",
                    "display": "flex"
                },
                "capInsets": {},
                "ParentId": "13d4ce86-9003-41ea-8c1f-a4a68f91fe65",
                "position": "absolute",
                "edgeOffsets": 532
            },
            "children": [],
            "id": "661331a1-984d-47a1-a5b1-6f6bbe54da2e",
            "thunkableVersion": 420,
            "name": "Image3"
        },
        {
            "type": "Button",
            "translatedName": "Button",
            "properties": {
                "Text": "Take a picture instead",
                "TextColor": "#FFFFFF",
                "FontSize": 16,
                "CustomFont": "",
                "BackgroundColor": "rgba(93, 122, 252, 100)",
                "Height": 49,
                "Width": 311,
                "Visible": true,
                "X": 32,
                "Y": 397,
                "RelativeX": 32,
                "RelativeY": 397,
                "ResizeMode": "STRETCH",
                "style": {
                    "marginTop": 0,
                    "marginBottom": 0,
                    "marginLeft": 0,
                    "marginRight": 0,
                    "paddingTop": 0,
                    "paddingBottom": 0,
                    "paddingLeft": 0,
                    "paddingRight": 0,
                    "borderRadius": 15,
                    "shadowColor": "rgba(0, 0, 0, 0)",
                    "shadowOpacity": 0,
                    "scaledShadowOpacity": 0,
                    "shadowRadius": 0,
                    "shadowOffset": {
                        "width": 0,
                        "height": 0
                    },
                    "position": "absolute",
                    "left": "30.72289646868725%",
                    "top": "63.15727646993841%",
                    "display": "flex"
                },
                "FontBold": false,
                "FontItalic": false,
                "Raised": false,
                "Disabled": false,
                "ParentId": "13d4ce86-9003-41ea-8c1f-a4a68f91fe65",
                "position": "absolute",
                "edgeOffsets": 397
            },
            "children": [],
            "id": "865f9eda-4103-413b-a31f-35cee4b1d3b6",
            "thunkableVersion": 420,
            "name": "Navigate to Picture"
        },
        {
            "type": "Button",
            "translatedName": "Button",
            "properties": {
                "Text": "Untimed Record",
                "TextColor": "#FFFFFF",
                "FontSize": 16,
                "CustomFont": "",
                "BackgroundColor": "rgba(93, 122, 252, 100)",
                "Height": 49,
                "Width": 311,
                "Visible": true,
                "X": 32,
                "Y": 340,
                "RelativeX": 32,
                "RelativeY": 340,
                "ResizeMode": "STRETCH",
                "style": {
                    "marginTop": 0,
                    "marginBottom": 0,
                    "marginLeft": 0,
                    "marginRight": 0,
                    "paddingTop": 0,
                    "paddingBottom": 0,
                    "paddingLeft": 0,
                    "paddingRight": 0,
                    "borderRadius": 15,
                    "shadowColor": "rgba(0, 0, 0, 0)",
                    "shadowOpacity": 0,
                    "scaledShadowOpacity": 0,
                    "shadowRadius": 0,
                    "shadowOffset": {
                        "width": 0,
                        "height": 0
                    },
                    "position": "absolute",
                    "left": "32.3293221714985%",
                    "top": "38.4792514001945%",
                    "display": "flex"
                },
                "FontBold": false,
                "FontItalic": false,
                "Raised": false,
                "Disabled": false,
                "ParentId": "13d4ce86-9003-41ea-8c1f-a4a68f91fe65",
                "position": "absolute",
                "edgeOffsets": 340
            },
            "children": [],
            "id": "f3f3e12f-dc8e-4110-91ab-c30942b0219e",
            "thunkableVersion": 420,
            "name": "Untimed"
        },
        {
            "type": "Button",
            "translatedName": "Button",
            "properties": {
                "Text": "Record 5 Seconds",
                "TextColor": "#FFFFFF",
                "FontSize": 16,
                "CustomFont": "",
                "BackgroundColor": "rgba(93, 122, 252, 100)",
                "Height": 49,
                "Width": 311,
                "Visible": true,
                "X": 32,
                "Y": 283,
                "RelativeX": 32,
                "RelativeY": 283,
                "ResizeMode": "STRETCH",
                "style": {
                    "marginTop": 0,
                    "marginBottom": 0,
                    "marginLeft": 0,
                    "marginRight": 0,
                    "paddingTop": 0,
                    "paddingBottom": 0,
                    "paddingLeft": 0,
                    "paddingRight": 0,
                    "borderRadius": 15,
                    "shadowColor": "rgba(0, 0, 0, 0)",
                    "shadowOpacity": 0,
                    "scaledShadowOpacity": 0,
                    "shadowRadius": 0,
                    "shadowOffset": {
                        "width": 0,
                        "height": 0
                    },
                    "position": "absolute",
                    "left": "32.65060731206074%",
                    "top": "35.76976299804186%",
                    "display": "flex"
                },
                "FontBold": false,
                "FontItalic": false,
                "Raised": false,
                "Disabled": false,
                "ParentId": "13d4ce86-9003-41ea-8c1f-a4a68f91fe65",
                "position": "absolute",
                "edgeOffsets": 283
            },
            "children": [],
            "id": "c3178578-df59-4b51-b1fa-bbe194d543b7",
            "thunkableVersion": 420,
            "name": "Timed"
        },
        {
            "type": "Video",
            "label": "Video",
            "translatedName": "Video",
            "properties": {
                "Play": false,
                "Height": 257,
                "Width": 357,
                "Visible": true,
                "X": 9,
                "Y": 24,
                "RelativeX": 9,
                "RelativeY": 24,
                "ResizeMode": "STRETCH",
                "ParentId": "13d4ce86-9003-41ea-8c1f-a4a68f91fe65",
                "position": "absolute",
                "edgeOffsets": 24,
                "style": {
                    "position": "absolute",
                    "left": "13.98233068994729%",
                    "top": "5.784758014219301%",
                    "display": "flex"
                }
            },
            "children": [],
            "id": "4db1c939-4554-47e7-b3b5-8d12c6d4b5ea",
            "thunkableVersion": 420,
            "name": "Video1"
        }
    ],
    "id": "13d4ce86-9003-41ea-8c1f-a4a68f91fe65",
    "thunkableVersion": 420,
    "name": "Video Screen"
}